Metadata-Version: 2.1
Name: iamlogic-idm
Version: 1.1
Summary: IAMLOGIC IDM package
Home-page: UNKNOWN
Author-email: info@iamlogic.com
License: UNKNOWN
Platform: UNKNOWN
Classifier: Development Status :: 3 - Alpha
Classifier: Intended Audience :: Developers
Classifier: Programming Language :: Python :: 3
Classifier: Programming Language :: Python :: 3.8
Classifier: Programming Language :: Python :: 3.9
